TensorflowRumenChuyiFix1/README.md
TensorflowRumenChuyiFix1/__init__.py
TensorflowRumenChuyiFix1/__main__.py
TensorflowRumenChuyiFix1/file.epub
TensorflowRumenChuyiFix1/index.html
TensorflowRumenChuyiFix1/css/__init__.py
TensorflowRumenChuyiFix1/css/annotations.css
TensorflowRumenChuyiFix1/css/main.css
TensorflowRumenChuyiFix1/css/normalize.css
TensorflowRumenChuyiFix1/css/popup.css
TensorflowRumenChuyiFix1/font/__init__.py
TensorflowRumenChuyiFix1/font/fontello.eot
TensorflowRumenChuyiFix1/font/fontello.svg
TensorflowRumenChuyiFix1/font/fontello.ttf
TensorflowRumenChuyiFix1/font/fontello.woff
TensorflowRumenChuyiFix1/img/__init__.py
TensorflowRumenChuyiFix1/img/annotator-glyph-sprite.png
TensorflowRumenChuyiFix1/img/annotator-icon-sprite.png
TensorflowRumenChuyiFix1/img/apple-touch-icon.png
TensorflowRumenChuyiFix1/img/cancelfullscreen.png
TensorflowRumenChuyiFix1/img/close.png
TensorflowRumenChuyiFix1/img/fullscreen.png
TensorflowRumenChuyiFix1/img/loader.gif
TensorflowRumenChuyiFix1/img/menu-icon.png
TensorflowRumenChuyiFix1/img/save.png
TensorflowRumenChuyiFix1/img/saved.png
TensorflowRumenChuyiFix1/img/settings-s.png
TensorflowRumenChuyiFix1/img/settings.png
TensorflowRumenChuyiFix1/img/star.png
TensorflowRumenChuyiFix1/js/__init__.py
TensorflowRumenChuyiFix1/js/epub.js
TensorflowRumenChuyiFix1/js/epub.min.js
TensorflowRumenChuyiFix1/js/epub.min.map
TensorflowRumenChuyiFix1/js/hooks.min.js
TensorflowRumenChuyiFix1/js/hooks.min.map
TensorflowRumenChuyiFix1/js/reader.js
TensorflowRumenChuyiFix1/js/reader.js.map
TensorflowRumenChuyiFix1/js/reader.min.js
TensorflowRumenChuyiFix1/js/reader.min.map
TensorflowRumenChuyiFix1/js/hooks/__init__.py
TensorflowRumenChuyiFix1/js/hooks/extensions/__init__.py
TensorflowRumenChuyiFix1/js/hooks/extensions/highlight.js
TensorflowRumenChuyiFix1/js/libs/__init__.py
TensorflowRumenChuyiFix1/js/libs/jquery.min.js
TensorflowRumenChuyiFix1/js/libs/localforage.min.js
TensorflowRumenChuyiFix1/js/libs/screenfull.js
tensorflow_rumen_chuyi_fix1-2025.3.24.1.dist-info/METADATA
tensorflow_rumen_chuyi_fix1-2025.3.24.1.dist-info/WHEEL
tensorflow_rumen_chuyi_fix1-2025.3.24.1.dist-info/entry_points.txt
tensorflow_rumen_chuyi_fix1-2025.3.24.1.dist-info/top_level.txt
tensorflow_rumen_chuyi_fix1-2025.3.24.1.dist-info/RECORD
